README.rst
setup.py
reprec/__init__.py
reprec.egg-info/PKG-INFO
reprec.egg-info/SOURCES.txt
reprec.egg-info/dependency_links.txt
reprec.egg-info/entry_points.txt
reprec.egg-info/top_level.txt
setops/__init__.py